[
    {
        "email": "admin@uma.pt",
        "pass": "admin",
        "numero": "0000000",
        "isAdmin": true,
        "hasPass": false,
        "getPass": false,
        "emittedPass": false,
        "typePass": "",
        "payed": false
    },
    {
        "email": "student@uma.pt",
        "pass": "student",
        "numero": "9999999",
        "isAdmin": false,
        "hasPass": false,
        "getPass": false,
        "emittedPass": false,
        "typePass": "",
        "payed": false
    }
]